[{"subnaam": ["\"Vishera\", boxed"], "naam": ["AMD", "FX-4300, 3,8 GHz (4,0 GHz Turbo Boost) AM3+ processor"], "info": ["\n          3.800 MHz\u00a0\n        ", "\n          4  cores\u00a0\n        ", "\n          AM3+\u00a0\n        "], "stock": ["Direct leverbaar"]},
{"subnaam": ["\"Vishera\""], "naam": ["AMD", "FX-4350, 4,2 GHz (4,3 GHz Turbo Boost) AM3+ processor"], "info": ["\n          4.200 MHz\u00a0\n        ", "\n          4  cores\u00a0\n        ", "\n          AM3+\u00a0\n        "], "stock": ["Direct leverbaar"]},
{"subnaam": ["\"Vishera\", boxed"], "naam": ["AMD", "FX-6300, 3,5 GHz (4,1 GHz Turbo Boost) AM3+ processor"], "info": ["\n          3.500 MHz\u00a0\n        ", "\n          6  cores\u00a0\n        ", "\n          AM3+\u00a0\n        "], "stock": ["Direct leverbaar"]},
{"subnaam": ["\"Vishera\", boxed"], "naam": ["AMD", "FX-6350, 3,9 GHz (4,2 GHz Turbo Boost) AM3+ processor"], "info": ["\n          3.900 MHz\u00a0\n        ", "\n          6  cores\u00a0\n        ", "\n          AM3+\u00a0\n        "], "stock": ["Levertijd: 3-5 werkdagen"]},
{"subnaam": ["\"Vishera\", boxed"], "naam": ["AMD", "FX-8320, 3,5 GHz (4,0 GHz Turbo Boost) AM3+ processor"], "info": ["\n          3.500 MHz\u00a0\n        ", "\n          8  cores\u00a0\n        ", "\n          AM3+\u00a0\n        "], "stock": ["Levertijd: 3-5 werkdagen"]},
{"subnaam": ["\"Vishera\", boxed"], "naam": ["AMD", "FX-8350, 4,0 GHz (4,2 GHz Turbo Boost) AM3+ processor"], "info": ["\n          4.000 MHz\u00a0\n        ", "\n          8  cores\u00a0\n        ", "\n          AM3+\u00a0\n        "], "stock": ["Direct leverbaar"]},
{"subnaam": ["mPGA, \"Vishera\", zonder koeler"], "naam": ["AMD", "FX-9370, 4,4 GHz (4,7 GHz Turbo Boost) AM3+ processor"], "info": ["\n          4.400 MHz\u00a0\n        ", "\n          8  cores\u00a0\n        ", "\n          AM3+\u00a0\n        "], "stock": ["Levertijd: 3-5 werkdagen"]},
{"subnaam": ["mPGA, \"Vishera\", zonder koeler"], "naam": ["AMD", "FX-9590, 4,7 GHz (5,0 GHz Turbo Boost) AM3+ processor"], "info": ["\n          4.700 MHz\u00a0\n        ", "\n          8  cores\u00a0\n        ", "\n          AM3+\u00a0\n        "], "stock": ["Levertijd: 3-5 werkdagen"]},
{"subnaam": ["\"Trinity\", uPGA"], "naam": ["AMD", "A10-5700, 3,4 GHz (4,0 GHz Turbo Boost) FM2 processor"], "info": ["\n          3.400 MHz\u00a0\n        ", "\n          4  cores\u00a0\n        ", "\n          FM2\u00a0\n        "], "stock": ["Levertijd: 3-5 werkdagen"]},
{"subnaam": ["\"Trinity\", Black Edition, boxed"], "naam": ["AMD", "A10-5800K, 3,8 GHz (4,2 GHz Turbo Boost) FM2 processor"], "info": ["\n          3.800 MHz\u00a0\n        ", "\n          4  cores\u00a0\n        ", "\n          FM2\u00a0\n        "], "stock": ["Direct leverbaar"]},
{"subnaam": ["\"Richland\", boxed"], "naam": ["AMD", "A10-6700, 3,7 GHz (4,3 GHz Turbo Boost) FM2 processor"], "info": ["\n          3.700 MHz\u00a0\n        ", "\n          4  cores\u00a0\n        ", "\n          FM2\u00a0\n        "], "stock": ["Levertijd: 3-5 werkdagen"]},
{"subnaam": ["\"Richland\", Black Edition, boxed"], "naam": ["AMD", "A10-6800K, 4,1 GHz (4,4 GHz Turbo Boost) FM2 processor"], "info": ["\n          4.100 MHz\u00a0\n        ", "\n          4  cores\u00a0\n        ", "\n          FM2\u00a0\n        "], "stock": ["Direct leverbaar"]},
{"subnaam": ["\"Richland\", boxed"], "naam": ["AMD", "A4-4000, 3,0 GHz FM2 processor"], "info": ["\n          3.000 MHz\u00a0\n        ", "\n          2  cores\u00a0\n        ", "\n          FM2\u00a0\n        "], "stock": ["Direct leverbaar"]},
{"subnaam": ["\"Richland\", boxed"], "naam": ["AMD", "A4-4020, 3,2 GHz FM2 processor"], "info": ["\n          3.200 MHz\u00a0\n        ", "\n          2  cores\u00a0\n        ", "\n          FM2\u00a0\n        "], "stock": ["Levertijd: 3-5 werkdagen"]},
{"subnaam": ["\"Trinity\", boxed"], "naam": ["AMD", "A4-5300, 3,5 GHz FM2 processor"], "info": ["\n          3.400 MHz\u00a0\n        ", "\n          2  cores\u00a0\n        ", "\n          FM2\u00a0\n        "], "stock": ["Levertijd: 3-5 werkdagen"]},
{"subnaam": ["\"Richland\""], "naam": ["AMD", "A4-6300 3,7GHz (3,9 GHz Turbo Boost) FM2 processor"], "info": ["\n          3.700 MHz\u00a0\n        ", "\n          2  cores\u00a0\n        ", "\n          FM2\u00a0\n        "], "stock": ["Levertijd: 3-5 werkdagen"]},
{"subnaam": ["\"Richland\""], "naam": ["AMD", "A4-6320, 3,8 GHz FM2 processor"], "info": ["\n          3.800 MHz\u00a0\n        ", "\n          2  cores\u00a0\n        ", "\n          FM2\u00a0\n        "], "stock": ["Levertijd: 3-5 werkdagen"]},
{"subnaam": ["\"Trinity\", Black Edition, boxed"], "naam": ["AMD", "A6-5400K, 3,6 GHz (3,8 GHz Turbo Boost) FM2 processor"], "info": ["\n          3.600 MHz\u00a0\n        ", "\n          2  cores\u00a0\n        ", "\n          FM2\u00a0\n        "], "stock": ["Levertijd: 3-5 werkdagen"]},
{"subnaam": ["\"Richland\", Black Edition, boxed"], "naam": ["AMD", "A6-6400K, 3,9 GHz (4,1 GHz Turbo Boost) FM2 processor"], "info": ["\n          3.900 MHz\u00a0\n        ", "\n          2  cores\u00a0\n        ", "\n          FM2\u00a0\n        "], "stock": ["Direct leverbaar"]},
{"subnaam": ["\"Richland\", Black Edition, boxed"], "naam": ["AMD", "A6-6420K, 4,0 GHz (4,2 GHz Turbo Boost) FM2 processor"], "info": ["\n          4.000 MHz\u00a0\n        ", "\n          2  cores\u00a0\n        ", "\n          FM2\u00a0\n        "], "stock": ["Levertijd: 3-5 werkdagen"]},
{"subnaam": ["\"Trinity\", Black Edition, boxed"], "naam": ["AMD", "A8-5600K, 3,6 GHz (3,9 GHz Turbo Boost) FM2 processor"], "info": ["\n          3.600 MHz\u00a0\n        ", "\n          4  cores\u00a0\n        ", "\n          FM2\u00a0\n        "], "stock": ["Levertijd: 3-5 werkdagen"]},
{"subnaam": ["\"Richland\", boxed"], "naam": ["AMD", "A8-6500, 3,5 GHz (4,1 GHz Turbo Boost) FM2 processor"], "info": ["\n          3.500 MHz\u00a0\n        ", "\n          4  cores\u00a0\n        ", "\n          FM2\u00a0\n        "], "stock": ["Levertijd: 3-5 werkdagen"]},
{"subnaam": ["\"Richland\", Black Edition, boxed"], "naam": ["AMD", "A8-6600K, 3,9 GHz (4,2 GHz Turbo Boost) FM2 processor"], "info": ["\n          3.900 MHz\u00a0\n        ", "\n          4  cores\u00a0\n        ", "\n          FM2\u00a0\n        "], "stock": ["Direct leverbaar"]},
{"subnaam": ["uPGA, \"Trinity\", Black Edition"], "naam": ["AMD", "Athlon\u2122 II X4 740, 3,2 GHz (3,7 GHz Turbo Boost) FM2 processor"], "info": ["\n          3.200 MHz\u00a0\n        ", "\n          4  cores\u00a0\n        ", "\n          FM2\u00a0\n        "], "stock": ["Levertijd: 3-5 werkdagen"]},
{"subnaam": ["uPGA, \"Trinity\", Black Edition"], "naam": ["AMD", "Athlon\u2122 II X4 750K, 3,4 GHz (4,0 GHz Turbo Boost) FM2 processor"], "info": ["\n          3.400 MHz\u00a0\n        ", "\n          4  cores\u00a0\n        ", "\n          FM2\u00a0\n        "], "stock": ["Direct leverbaar"]},
{"subnaam": ["uPGA, \"Richland\", Black Edition, boxed"], "naam": ["AMD", "Athlon\u2122 II X4 760K, 3,8 GHz (4,1 GHz Turbo Boost) FM2 processor"], "info": ["\n          3.800 MHz\u00a0\n        ", "\n          4  cores\u00a0\n        ", "\n          FM2\u00a0\n        "], "stock": ["Direct leverbaar"]},
{"subnaam": ["\"Kaveri\""], "naam": ["AMD", "A10-7700K, 3,4 GHz (3,8 GHz Turbo Boost) FM2+ processor"], "info": ["\n          3.400 MHz\u00a0\n        ", "\n          4  cores\u00a0\n        ", "\n          FM2+\u00a0\n        "], "stock": ["Levertijd: 3-5 werkdagen"]},
{"subnaam": ["\"Kaveri\", boxed"], "naam": ["AMD", "A10-7800 3,5 GHz (3,9 GHz Turbo Boost) FM2+ processor"], "info": ["\n          3.500 MHz\u00a0\n        ", "\n          4  cores\u00a0\n        ", "\n          FM2+\u00a0\n        "], "stock": ["Levertijd: 3-5 werkdagen"]},
{"subnaam": ["\"Kaveri\", Black Edition"], "naam": ["AMD", "A10-7850K, 3,4 GHz (3,7 GHz Turbo Boost) FM2+ processor"], "info": ["\n          3.700 MHz\u00a0\n        ", "\n          4  cores\u00a0\n        ", "\n          FM2+\u00a0\n        "], "stock": ["Direct leverbaar"]},
{"subnaam": ["\"Kaveri\", boxed"], "naam": ["AMD", "A6-7400K 3,5 GHz (3,9 GHz Turbo Boost) FM2+ processor"], "info": ["\n          3.500 MHz\u00a0\n        ", "\n          2  cores\u00a0\n        ", "\n          FM2+\u00a0\n        "], "stock": ["Direct leverbaar"]},
{"subnaam": ["\"Kaveri\", boxed"], "naam": ["AMD", "A8-7600, 3,1 GHz (3,8 GHz Turbo Boost) FM2+ processor"], "info": ["\n          3.100 MHz\u00a0\n        ", "\n          4  cores\u00a0\n        ", "\n          FM2+\u00a0\n        "], "stock": ["Levertijd: 3-5 werkdagen"]},
{"subnaam": ["mPGA, \"Kabini\", boxed"], "naam": ["AMD", "Athlon 5150, 1,6 GHz AM1 processor"], "info": ["\n          1.600 MHz\u00a0\n        ", "\n          4  cores\u00a0\n        ", "\n          AM1\u00a0\n        "], "stock": ["Direct leverbaar"]},
{"subnaam": ["\"Kabini\", boxed"], "naam": ["AMD", "Athlon\u2122 5350, 2,05 GHz AM1 processor"], "info": ["\n          2.050 MHz\u00a0\n        ", "\n          4  cores\u00a0\n        ", "\n          \u00a0\n        "], "stock": ["Levertijd: 3-5 werkdagen"]},
{"subnaam": ["mPGA, \"Kabini\", boxed"], "naam": ["AMD", "Sempron 2650, 1,45 GHz AM1 processor"], "info": ["\n          1.450 MHz\u00a0\n        ", "\n          2  cores\u00a0\n        ", "\n          \u00a0\n        "], "stock": ["Direct leverbaar"]},
{"subnaam": ["mPGA, \"Kabini\", boxed"], "naam": ["AMD", "Sempron 3850, 1,3 GHz AM1 processor"], "info": ["\n          1.300 MHz\u00a0\n        ", "\n          4  cores\u00a0\n        ", "\n          \u00a0\n        "], "stock": ["Direct leverbaar"]},
{"subnaam": ["FC-LGA4, \"Haswell-R\""], "naam": ["Intel\u00ae", "Celeron\u00ae G1840, 2,8 GHz 1150 processor"], "info": ["\n          2.800 MHz\u00a0\n        ", "\n          2  cores\u00a0\n        ", "\n          1150\u00a0\n        "], "stock": ["Direct leverbaar"]},
{"subnaam": ["FC-LGA4, \"Haswell-R\""], "naam": ["Intel\u00ae", "Celeron\u00ae G1850, 2,9 GHz 1150 processor"], "info": ["\n          2.900 MHz\u00a0\n        ", "\n          2  cores\u00a0\n        ", "\n          1150\u00a0\n        "], "stock": ["Direct leverbaar"]},
{"subnaam": ["FC-LGA4, \"Haswell\", boxed"], "naam": ["Intel\u00ae", "Core\u2122 i3-4130, 3,4 GHz 1150 processor"], "info": ["\n          3.400 MHz\u00a0\n        ", "\n          2  cores\u00a0\n        ", "\n          1150\u00a0\n        "], "stock": ["Levertijd: 3-5 werkdagen"]},
{"subnaam": ["FC-LGA4, \"Haswell-R\""], "naam": ["Intel\u00ae", "Core\u2122 i3-4150, 3,5 GHz 1150 processor"], "info": ["\n          3.500 MHz\u00a0\n        ", "\n          2  cores\u00a0\n        ", "\n          1150\u00a0\n        "], "stock": ["Direct leverbaar"]},
{"subnaam": ["FC-LGA4, \"Haswell\", boxed"], "naam": ["Intel\u00ae", "Core\u2122 i3-4160, 3,6 GHz 1150 processor"], "info": ["\n          3.600 MHz\u00a0\n        ", "\n          2  cores\u00a0\n        ", "\n          1150\u00a0\n        "], "stock": ["Direct leverbaar"]},
{"subnaam": ["FC-LGA4, \"Haswell\", boxed"], "naam": ["Intel\u00ae", "Core\u2122 i3-4330, 3,5 GHz 1150 processor"], "info": ["\n          3.500 MHz\u00a0\n        ", "\n          2  cores\u00a0\n        ", "\n          1150\u00a0\n        "], "stock": ["Direct leverbaar"]},
{"subnaam": ["FC-LGA4, \"Haswell\", boxed"], "naam": ["Intel\u00ae", "Core\u2122 i3-4340, 3,6 GHz 1150 processor"], "info": ["\n          3.600 MHz\u00a0\n        ", "\n          2  cores\u00a0\n        ", "\n          1150\u00a0\n        "], "stock": ["Direct leverbaar"]},
{"subnaam": ["FC-LGA4, \"Haswell-R\""], "naam": ["Intel\u00ae", "Core\u2122 i3-4350, 3,6 GHz 1150 processor"], "info": ["\n          3.600 MHz\u00a0\n        ", "\n          2  cores\u00a0\n        ", "\n          1150\u00a0\n        "], "stock": ["Direct leverbaar"]},
{"subnaam": ["FC-LGA4, \"Haswell-R\""], "naam": ["Intel\u00ae", "Core\u2122 i3-4360, 3,7 GHz 1150 processor"], "info": ["\n          3.700 MHz\u00a0\n        ", "\n          2  cores\u00a0\n        ", "\n          1150\u00a0\n        "], "stock": ["Direct leverbaar"]},
{"subnaam": ["FC-LGA4, \"Haswell\", boxed"], "naam": ["Intel\u00ae", "Core\u2122 i3-4370, 3,8 GHz 1150 processor"], "info": ["\n          3.800 MHz\u00a0\n        ", "\n          2  cores\u00a0\n        ", "\n          1150\u00a0\n        "], "stock": ["Direct leverbaar"]},
{"subnaam": ["FC-LGA4, \"Haswell\", boxed"], "naam": ["Intel\u00ae", "Core\u2122 i5-4430, 3,0 GHz (3,2 GHz Turbo Boost) 1150 processor"], "info": ["\n          3.000 MHz\u00a0\n        ", "\n          4  cores\u00a0\n        ", "\n          1150\u00a0\n        "], "stock": ["Levertijd: 3-5 werkdagen"]},
{"subnaam": ["FC-LGA4, \"Haswell\", boxed"], "naam": ["Intel\u00ae", "Core\u2122 i5-4440, 3,1 GHz (3,3 GHz Turbo Boost) 1150 processor"], "info": ["\n          3.100 MHz\u00a0\n        ", "\n          4  cores\u00a0\n        ", "\n          1150\u00a0\n        "], "stock": ["Levertijd: 3-5 werkdagen"]},
{"subnaam": ["FC-LGA4, \"Haswell-R\""], "naam": ["Intel\u00ae", "Core\u2122 i5-4460, 3,2 GHz (3,4 GHz Turbo Boost) 1150 processor"], "info": ["\n          3.200 MHz\u00a0\n        ", "\n          4  cores\u00a0\n        ", "\n          1150\u00a0\n        "], "stock": ["Direct leverbaar"]},
{"subnaam": ["FC-LGA4, \"Haswell\", boxed"], "naam": ["Intel\u00ae", "Core\u2122 i5-4570, 3,2 GHz (3,6 GHz Turbo Boost) 1150 processor"], "info": ["\n          3.200 MHz\u00a0\n        ", "\n          4  cores\u00a0\n        ", "\n          1150\u00a0\n        "], "stock": ["Direct leverbaar"]},
{"subnaam": ["FC-LGA4, \"Haswell\", boxed"], "naam": ["Intel\u00ae", "Core\u2122 i5-4570S, 2,9 GHz (3,6 GHz Turbo Boost) 1150 processor"], "info": ["\n          2.900 MHz\u00a0\n        ", "\n          4  cores\u00a0\n        ", "\n          1150\u00a0\n        "], "stock": ["Direct leverbaar"]},
{"subnaam": ["FC-LGA4, \"Haswell-R\""], "naam": ["Intel\u00ae", "Core\u2122 i5-4590, 3,3 GHz (3,7 GHz Turbo Boost) 1150 processor"], "info": ["\n          3.300 MHz\u00a0\n        ", "\n          4  cores\u00a0\n        ", "\n          1150\u00a0\n        "], "stock": ["Direct leverbaar"]},
{"subnaam": ["FC-LGA4, \"Haswell-R\""], "naam": ["Intel\u00ae", "Core\u2122 i5-4590S, 3,0 GHz (3,7 GHz Turbo Boost) 1150 processor"], "info": ["\n          3.000 MHz\u00a0\n        ", "\n          4  cores\u00a0\n        ", "\n          1150\u00a0\n        "], "stock": ["Direct leverbaar"]},
{"subnaam": ["FC-LGA4, \"Haswell\", boxed"], "naam": ["Intel\u00ae", "Core\u2122 i5-4670, 3,4 GHz (3,8 GHz Turbo Boost) 1150 processor"], "info": ["\n          3.400 MHz\u00a0\n        ", "\n          4  cores\u00a0\n        ", "\n          1150\u00a0\n        "], "stock": ["Direct leverbaar"]},
{"subnaam": ["FC-LGA4, \"Haswell\", boxed"], "naam": ["Intel\u00ae", "Core\u2122 i5-4670K, 3,4 GHz (3,8 GHz Turbo Boost) 1150 processor"], "info": ["\n          3.400 MHz\u00a0\n        ", "\n          4  cores\u00a0\n        ", "\n          1150\u00a0\n        "], "stock": ["Levertijd: 1-2 werkdagen"]},
{"subnaam": ["FC-LGA4, \"Haswell-R\""], "naam": ["Intel\u00ae", "Core\u2122 i5-4690, 3,5 GHz (3,9 GHz Turbo Boost) 1150 processor"], "info": ["\n          3.500 MHz\u00a0\n        ", "\n          4  cores\u00a0\n        ", "\n          1150\u00a0\n        "], "stock": ["Direct leverbaar"]},
{"subnaam": ["FC-LGA4, \"Haswell-R\", boxed"], "naam": ["Intel\u00ae", "Core\u2122 i5-4690K, 3,5 GHz (3,9 GHz Turbo Boost) 1150 processor"], "info": ["\n          3.500 MHz\u00a0\n        ", "\n          4  cores\u00a0\n        ", "\n          1150\u00a0\n        "], "stock": ["Direct leverbaar"]},
{"subnaam": ["FC-LGA4, \"Haswell-R\""], "naam": ["Intel\u00ae", "Core\u2122 i5-4690S, 3,2 GHz (3,9 GHz Turbo Boost) 1150 processor"], "info": ["\n          3.200 MHz\u00a0\n        ", "\n          4  cores\u00a0\n        ", "\n          1150\u00a0\n        "], "stock": ["Direct leverbaar"]},
{"subnaam": ["FC-LGA4, \"Haswell\", boxed"], "naam": ["Intel\u00ae", "Core\u2122 i7-4770, 3,4 GHz (3,9 GHz Turbo Boost) 1150 processor"], "info": ["\n          3.400 MHz\u00a0\n        ", "\n          4  cores\u00a0\n        ", "\n          1150\u00a0\n        "], "stock": ["Direct leverbaar"]},
{"subnaam": ["FC-LGA4, \"Haswell\", boxed"], "naam": ["Intel\u00ae", "Core\u2122 i7-4770K, 3,5 GHz (3,9 GHz Turbo Boost) 1150 processor"], "info": ["\n          3.500 MHz\u00a0\n        ", "\n          4  cores\u00a0\n        ", "\n          1150\u00a0\n        "], "stock": ["Direct leverbaar"]},
{"subnaam": ["FC-LGA4, \"Haswell\", boxed"], "naam": ["Intel\u00ae", "Core\u2122 i7-4770S, 3,1 GHz (3,9 GHz Turbo Boost) 1150 processor"], "info": ["\n          3.100 MHz\u00a0\n        ", "\n          4  cores\u00a0\n        ", "\n          1150\u00a0\n        "], "stock": ["Levertijd: 3-5 werkdagen"]},
{"subnaam": ["FC-LGA4, \"Haswell\", boxed"], "naam": ["Intel\u00ae", "Core\u2122 i7-4771, 3,5 GHz (3,9 GHz Turbo Boost) 1150 processor"], "info": ["\n          3.500 MHz\u00a0\n        ", "\n          4  cores\u00a0\n        ", "\n          1150\u00a0\n        "], "stock": ["Direct leverbaar"]},
{"subnaam": ["FC-LGA4, \"Haswell-R\""], "naam": ["Intel\u00ae", "Core\u2122 i7-4790, 3,6 GHz (4,0 GHz Turbo Boost) 1150 processor"], "info": ["\n          3.600 MHz\u00a0\n        ", "\n          4  cores\u00a0\n        ", "\n          1150\u00a0\n        "], "stock": ["Direct leverbaar"]},
{"subnaam": ["FC-LGA4, \"Haswell-R\", boxed"], "naam": ["Intel\u00ae", "Core\u2122 i7-4790K, 4,0 GHz (4,4 GHz Turbo Boost) 1150 processor"], "info": ["\n          4.000 MHz\u00a0\n        ", "\n          4  cores\u00a0\n        ", "\n          1150\u00a0\n        "], "stock": ["Direct leverbaar"]},
{"subnaam": ["FC-LGA4, \"Haswell-R\""], "naam": ["Intel\u00ae", "Core\u2122 i7-4790S, 3,2 GHz (4,0 GHz Turbo Boost) 1150 processor"], "info": ["\n          3.200 MHz\u00a0\n        ", "\n          4  cores\u00a0\n        ", "\n          1150\u00a0\n        "], "stock": ["Levertijd: 1-2 werkdagen"]},
{"subnaam": ["FC-LGA4, \"Haswell-R\""], "naam": ["Intel\u00ae", "Pentium\u00ae G3240, 3,1 GHz 1150 processor"], "info": ["\n          3.100 MHz\u00a0\n        ", "\n          2  cores\u00a0\n        ", "\n          1150\u00a0\n        "], "stock": ["Direct leverbaar"]},
{"subnaam": ["FC-LGA4, \"Haswell\", boxed"], "naam": ["Intel\u00ae", "Pentium\u00ae G3250, 3,2 GHz 1150 processor"], "info": ["\n          3.200 MHz\u00a0\n        ", "\n          2  cores\u00a0\n        ", "\n          1150\u00a0\n        "], "stock": ["Levertijd: 3-5 werkdagen"]},
{"subnaam": ["FC-LGA4, \"Haswell-R\", 20th Anniversary, boxed"], "naam": ["Intel\u00ae", "Pentium\u00ae G3258, 3,2 GHz 1150 processor"], "info": ["\n          3.200 MHz\u00a0\n        ", "\n          2  cores\u00a0\n        ", "\n          1150\u00a0\n        "], "stock": ["Direct leverbaar"]},
{"subnaam": ["FC-LGA4, \"Haswell-R\""], "naam": ["Intel\u00ae", "Pentium\u00ae G3440, 3,3 GHz 1150 processor"], "info": ["\n          3.300 MHz\u00a0\n        ", "\n          2  cores\u00a0\n        ", "\n          1150\u00a0\n        "], "stock": ["Direct leverbaar"]},
{"subnaam": ["FC-LGA4, \"Haswell-R\""], "naam": ["Intel\u00ae", "Pentium\u00ae G3450, 3,4 GHz 1150 processor"], "info": ["\n          3.400 MHz\u00a0\n        ", "\n          2  cores\u00a0\n        ", "\n          1150\u00a0\n        "], "stock": ["Levertijd: 3-5 werkdagen"]},
{"subnaam": ["FC-LGA4, \"Haswell\", boxed"], "naam": ["Intel\u00ae", "Pentium\u00ae G3460, 3,5 GHz 1150 processor"], "info": ["\n          3.500 MHz\u00a0\n        ", "\n          2  cores\u00a0\n        ", "\n          1150\u00a0\n        "], "stock": ["Levertijd: 3-5 werkdagen"]},
{"subnaam": ["\"Ivy Bridge\""], "naam": ["Intel\u00ae", "Celeron\u00ae G1620, 2,7 GHz 1155 processor"], "info": ["\n          2.700 MHz\u00a0\n        ", "\n          2  cores\u00a0\n        ", "\n          1155\u00a0\n        "], "stock": ["Direct leverbaar"]},
{"subnaam": ["FC-LGA4, \"Ivy Bridge\", boxed"], "naam": ["Intel\u00ae", "Core\u2122 i3-3220T, 2,8 GHz 1155 processor"], "info": ["\n          2.800 MHz\u00a0\n        ", "\n          2  cores\u00a0\n        ", "\n          1155\u00a0\n        "], "stock": ["Levertijd: 3-5 werkdagen"]},
{"subnaam": ["FC-LGA4, \"Ivy Bridge\", boxed"], "naam": ["Intel\u00ae", "Core\u2122 i3-3245, 3,4 GHz 1155 processor"], "info": ["\n          3.400 MHz\u00a0\n        ", "\n          2  cores\u00a0\n        ", "\n          1155\u00a0\n        "], "stock": ["Levertijd: 3-5 werkdagen"]},
{"subnaam": ["FC-LGA4, \"Ivy Bridge\", boxed"], "naam": ["Intel\u00ae", "Core\u2122 i3-3250, 3,5 GHz 1155 processor"], "info": ["\n          3.500 MHz\u00a0\n        ", "\n          2  cores\u00a0\n        ", "\n          1155\u00a0\n        "], "stock": ["Levertijd: 3-5 werkdagen"]},
{"subnaam": ["FC-LGA4, \"Ivy Bridge\", boxed"], "naam": ["Intel\u00ae", "Core\u2122 i5-3340, 3,1 GHz (3,3 GHz Turbo Boost) 1155 processor"], "info": ["\n          3.100 MHz\u00a0\n        ", "\n          4  cores\u00a0\n        ", "\n          1155\u00a0\n        "], "stock": ["Levertijd: 3-5 werkdagen"]},
{"subnaam": ["FC-LGA4, \"Ivy Bridge\", geen VGA, boxed"], "naam": ["Intel\u00ae", "Core\u2122 i5-3350P, 3,1 GHz (3,2 GHz Turbo Boost) 1155 processor"], "info": ["\n          3.100 MHz\u00a0\n        ", "\n          4  cores\u00a0\n        ", "\n          1155\u00a0\n        "], "stock": ["Levertijd: 3-5 werkdagen"]},
{"subnaam": ["FC-LGA4, \"Ivy Bridge\", Retail"], "naam": ["Intel\u00ae", "Core\u2122 i5-3470, 3,2 GHz (3,6 GHz Turbo Boost) 1155 processor"], "info": ["\n          3.200 MHz\u00a0\n        ", "\n          4  cores\u00a0\n        ", "\n          1155\u00a0\n        "], "stock": ["Direct leverbaar"]},
{"subnaam": ["FC-LGA4, \"Ivy Bridge\", Retail"], "naam": ["Intel\u00ae", "Core\u2122 i5-3470S, 2,9 GHz (3,5 GHz Turbo Boost) 1155 processor"], "info": ["\n          2.900 MHz\u00a0\n        ", "\n          4  cores\u00a0\n        ", "\n          1155\u00a0\n        "], "stock": ["Levertijd: 3-5 werkdagen"]},
{"subnaam": ["FC-LGA4, \"Ivy Bridge\", boxed"], "naam": ["Intel\u00ae", "Core\u2122 i5-3570, 3,4 GHz (3,8 GHz Turbo Boost) 1155 processor"], "info": ["\n          3.400 MHz\u00a0\n        ", "\n          4  cores\u00a0\n        ", "\n          1155\u00a0\n        "], "stock": ["Levertijd: 3-5 werkdagen"]},
{"subnaam": ["FC-LGA4, \"Ivy Bridge\", boxed"], "naam": ["Intel\u00ae", "Core\u2122 i5-3570K, 3,4 GHz (3,8 GHz Turbo Boost) 1155 processor"], "info": ["\n          3.400 MHz\u00a0\n        ", "\n          4  cores\u00a0\n        ", "\n          1155\u00a0\n        "], "stock": ["Direct leverbaar"]},
{"subnaam": ["FC-LGA4, \"Ivy Bridge\", boxed"], "naam": ["Intel\u00ae", "Core\u2122 i7-3770, 3,4 GHz (3,9 GHz Turbo Boost) 1155 processor"], "info": ["\n          3.400 MHz\u00a0\n        ", "\n          4  cores\u00a0\n        ", "\n          1155\u00a0\n        "], "stock": ["Direct leverbaar"]},
{"subnaam": ["FC-LGA4, \"Ivy Bridge\", boxed"], "naam": ["Intel\u00ae", "Core\u2122 i7-3770K, 3,5 GHz (3,9 GHz Turbo Boost) 1155 processor"], "info": ["\n          3.500 MHz\u00a0\n        ", "\n          4  cores\u00a0\n        ", "\n          1155\u00a0\n        "], "stock": ["Direct leverbaar"]},
{"subnaam": ["FC-LGA4, \"Ivy Bridge\", Retail"], "naam": ["Intel\u00ae", "Core\u2122 i7-3770S, 3,1 GHz (3,9 GHz Turbo Boost) 1155 processor"], "info": ["\n          3.100 MHz\u00a0\n        ", "\n          4  cores\u00a0\n        ", "\n          1155\u00a0\n        "], "stock": ["Levertermijn onbekend"]},
{"subnaam": ["FC-LGA4, \"Ivy Bridge\", boxed"], "naam": ["Intel\u00ae", "Pentium\u00ae G2030, 3,0 GHz 1155 processor"], "info": ["\n          3.000 MHz\u00a0\n        ", "\n          2  cores\u00a0\n        ", "\n          1155\u00a0\n        "], "stock": ["Levertermijn onbekend"]},
{"subnaam": ["\"Ivy Bridge\", Intel\u00ae HD Graphics"], "naam": ["Intel\u00ae", "Pentium\u00ae G2130, 3,2 GHz 1155 processor"], "info": ["\n          3.200 MHz\u00a0\n        ", "\n          2  cores\u00a0\n        ", "\n          1155\u00a0\n        "], "stock": ["Direct leverbaar"]},
{"subnaam": ["FC-LGA4, \"Haswell\", boxed"], "naam": ["Intel\u00ae", "Pentium\u00ae G3220, 3,0 GHz 1150 processor"], "info": ["\n          3.000 MHz\u00a0\n        ", "\n          2  cores\u00a0\n        ", "\n          1150\u00a0\n        "], "stock": ["Direct leverbaar"]},
{"subnaam": ["FC-LGA4, \"Haswell\", boxed"], "naam": ["Intel\u00ae", "Pentium\u00ae G3420, 3,2 GHz 1150 processor"], "info": ["\n          3.200 MHz\u00a0\n        ", "\n          2  cores\u00a0\n        ", "\n          1150\u00a0\n        "], "stock": ["Direct leverbaar"]},
{"subnaam": ["FC-LGA4, \"Haswell\", boxed"], "naam": ["Intel\u00ae", "Pentium\u00ae G3430, 3,3 GHz 1150 processor"], "info": ["\n          3.300 MHz\u00a0\n        ", "\n          2  cores\u00a0\n        ", "\n          1150\u00a0\n        "], "stock": ["Direct leverbaar"]},
{"subnaam": ["FC-LGA4, \"Sandy Bridge E\", WOF, Retail"], "naam": ["Intel\u00ae", "Core\u2122 i7-3820, 3,6 GHz (3,8 GHz Turbo Boost) 2011 processor"], "info": ["\n          3.600 MHz\u00a0\n        ", "\n          4  cores\u00a0\n        ", "\n          2011\u00a0\n        "], "stock": ["Direct leverbaar"]},
{"subnaam": ["FC-LGA4, \"Sandy Bridge E\", WOF, Retail"], "naam": ["Intel\u00ae", "Core\u2122 i7-3930K, 3,2 GHz (3,8 GHz Turbo Boost) 2011 processor"], "info": ["\n          3.200 MHz\u00a0\n        ", "\n          6  cores\u00a0\n        ", "\n          2011\u00a0\n        "], "stock": ["Direct leverbaar"]},
{"subnaam": ["FC-LGA4, \"Ivy Bridge-E\", WOF, Retail"], "naam": ["Intel\u00ae", "Core\u2122 i7-4820K, 3,7 GHz (3,9 GHz Turbo Boost) 2011 processor"], "info": ["\n          3.700 MHz\u00a0\n        ", "\n          4  cores\u00a0\n        ", "\n          2011\u00a0\n        "], "stock": ["Direct leverbaar"]},
{"subnaam": ["FC-LGA4, \"Ivy Bridge-E\", WOF, Retail"], "naam": ["Intel\u00ae", "Core\u2122 i7-4930K, 3,4 GHz (3,9 GHz Turbo Boost) 2011 processor"], "info": ["\n          3.400 MHz\u00a0\n        ", "\n          6  cores\u00a0\n        ", "\n          2011\u00a0\n        "], "stock": ["Levertijd: 3-5 werkdagen"]},
{"subnaam": ["FC-LGA4, \"Ivy Bridge-E\", WOF, Retail"], "naam": ["Intel\u00ae", "Core\u2122 i7-4960X, 3,6 GHz (4,0 GHz Turbo Boost) 2011 processor"], "info": ["\n          3.600 MHz\u00a0\n        ", "\n          6  cores\u00a0\n        ", "\n          2011\u00a0\n        "], "stock": ["Direct leverbaar"]},
{"subnaam": ["FC-LGA4, \"Haswell-E\", WOF, boxed"], "naam": ["Intel\u00ae", "Core\u2122 i7-5820K 3,3 GHz (3,6 GHz Turbo Boost) 2011-3 processor"], "info": ["\n          3.300 MHz\u00a0\n        ", "\n          6  cores\u00a0\n        ", "\n          2011-3\u00a0\n        "], "stock": ["Direct leverbaar"]},
{"subnaam": ["FC-LGA4, \"Haswell-E\", WOF, boxed"], "naam": ["Intel\u00ae", "Core\u2122 i7-5930K 3,5 GHz (3,7 GHz Turbo Boost) 2011-3 processor"], "info": ["\n          3.500 MHz\u00a0\n        ", "\n          6  cores\u00a0\n        ", "\n          2011-3\u00a0\n        "], "stock": ["Direct leverbaar"]},
{"subnaam": ["FC-LGA4, \"Haswell-E\", WOF, boxed"], "naam": ["Intel\u00ae", "Core\u2122 i7-5960X 3,0 GHz (3,5 GHz Turbo Boost) 2011-3 processor"], "info": ["\n          3.000 MHz\u00a0\n        ", "\n          8  cores\u00a0\n        ", "\n          2011-3\u00a0\n        "], "stock": ["Direct leverbaar"]}]